MANIFEST.in
README.rst
setup.cfg
setup.py
tw2/__init__.py
tw2.jqplugins.dynatree.egg-info/PKG-INFO
tw2.jqplugins.dynatree.egg-info/SOURCES.txt
tw2.jqplugins.dynatree.egg-info/dependency_links.txt
tw2.jqplugins.dynatree.egg-info/entry_points.txt
tw2.jqplugins.dynatree.egg-info/namespace_packages.txt
tw2.jqplugins.dynatree.egg-info/not-zip-safe
tw2.jqplugins.dynatree.egg-info/requires.txt
tw2.jqplugins.dynatree.egg-info/top_level.txt
tw2/jqplugins/__init__.py
tw2/jqplugins/dynatree/__init__.py
tw2/jqplugins/dynatree/base.py
tw2/jqplugins/dynatree/defaults.py
tw2/jqplugins/dynatree/samples.py
tw2/jqplugins/dynatree/widgets.py
tw2/jqplugins/dynatree/static/jquery/plugins/dynatree/1.1.1/GPL-LICENSE.txt
tw2/jqplugins/dynatree/static/jquery/plugins/dynatree/1.1.1/MIT-License.txt
tw2/jqplugins/dynatree/static/jquery/plugins/dynatree/1.1.1/jquery.dynatree.js
tw2/jqplugins/dynatree/static/jquery/plugins/dynatree/1.1.1/jquery.dynatree.min.js
tw2/jqplugins/dynatree/static/jquery/plugins/dynatree/1.1.1/skin/icons.gif
tw2/jqplugins/dynatree/static/jquery/plugins/dynatree/1.1.1/skin/loading.gif
tw2/jqplugins/dynatree/static/jquery/plugins/dynatree/1.1.1/skin/ui.dynatree.css
tw2/jqplugins/dynatree/static/jquery/plugins/dynatree/1.1.1/skin/vline.gif
tw2/jqplugins/dynatree/static/jquery/plugins/dynatree/1.1.1/skin-vista/icons.gif
tw2/jqplugins/dynatree/static/jquery/plugins/dynatree/1.1.1/skin-vista/jquery.dynatree.css
tw2/jqplugins/dynatree/static/jquery/plugins/dynatree/1.1.1/skin-vista/loading.gif
tw2/jqplugins/dynatree/templates/__init__.py
tw2/jqplugins/dynatree/templates/dynatree.mak